LICENSE
README.md
setup.py
pystep7/Client.py
pystep7/__init__.py
pystep7/constants.py
pystep7/exceptions.py
pystep7/tag.py
pystep7/utility.py
pystep7.egg-info/PKG-INFO
pystep7.egg-info/SOURCES.txt
pystep7.egg-info/dependency_links.txt
pystep7.egg-info/top_level.txt